{
    "": "Your link here",
    "meta:url": "",
    "meta:type": "",
    "meta:title": "",
    "meta:description": "",
    "meta:site_name": "",
    "meta:locale": "",
    "meta:publisher": "",
    "meta:section": "",
    "meta:image": "",
    "meta:twitter:card": "",
    "meta:twitter:site": "",
    "meta:twitter:creator": "",
    "meta:twitter:title": "",
    "meta:twitter:description": "",
    "meta:twitter:image": "",
    "short_url": "",
    "hero_title": "القصة التي لم ترو من المهاجرين البحر الأبيض المتوسط",
    "hero_subtitle": "و العنوان الفرعي تحت العنوان الرئيسي",
    "timestamp": "10 مايو 2016",
    "topic_label": "أوروبا",
    "topic_link": "",
    "author_name": "Vladimir Hernandez, Nassos Stylianou",
    "bbc_news": "BBC News",
    "intro_para_1": "مثال إدخال النص هنا",
    "intro_para_2": "مثال إدخال النص هنا",
    "intro_para_3": "مثال إدخال النص هنا",
    "intro_para_4": "",
    "intro_para_5": "",
    "intro_para_6": "",
    "section2_title": "",
    "section2_para_1": "",
    "section2_para_2": "",
    "section_2_map_alt_text": "النص هنا عن الخريطة",
    "map1_title": "أفغانستان وباكستان بالتفصيل",
    "map1_subtitle": "",
    "map2_title": "نيجيريا بالتفصيل",
    "map2_subtitle": "",
    "map3_title": "نيجيريا بالتفصيل",
    "map3_subtitle": "",
    "map_key_incidents": "قتلى",
    "map_key_deadormissing": "هجمات",
    "map_key_cemeteries": "القتلى:",
    "map_key_unmarkedgraves": "النوع:",
    "map_source": "",
    "map_footer_title": "كل دائرة تمثل هجوماً واحداً",
    "map_footer_graves_text": "أنواع الهجمات الأكثر تكراراً",
    "map1_label_1": "",
    "map1_label_2": "",
    "map1_label_3": "",
    "map1_label_4": "",
    "map1_label_5": "اليونان",
    "map1_label_6": "بلد تركيا",
    "map1_label_7": "يسبوس",
    "map1_label_8": "",
    "map2_label_1": "",
    "map2_label_2": "",
    "map2_label_3": "",
    "map2_label_4": "",
    "map2_label_5": "",
    "map2_label_6": "",
    "map2_label_7": "",
    "map2_label_8": "",
    "map3_label_1": "",
    "map3_label_2": "",
    "map3_label_3": "",
    "map3_label_4": "",
    "map3_label_5": "",
    "map3_label_6": "",
    "section3_title_1": "",
    "section3_para_1": "",
    "section3_para_2": "",
    "section3_title_2": "",
    "section3_para_3": "",
    "section3_para_4": "",
    "section3_para_5": "",
    "section3_video_title": "عنوان مقطع الفيديو",
    "section3_video_summary": "المدة: 1 دقيقة",
    "section4_title": "",
    "section4_para_1": "",
    "section4_para_2": "",
    "section4_para_3": "",
    "section4_para_4": "",
    "section_4_blockquote": "عنوان مقطع الفيديو",
    "section_4_blockquote_credit": "عنوان مقطع",
    "section5_title": "",
    "section5_para_1": "",
    "section5_para_2": "",
    "section5_para_3": "",
    "section5_para_4": "",
    "section5_para_5": "",
    "section5_para_6": "",
    "section5_video_title": "عنوان مقطع الفيديو",
    "section5_video_summary": "المدة: 1 دقيقة",
    "chart1_title": "",
    "chart1_subtitle": "",
    "chart1_impact_stat": "",
    "chart1_impact_text": "",
    "chart2_title": "",
    "chart2_subtitle": "",
    "chart2_impact_stat": "",
    "chart2_impact_text": "",
    "credits_title": "",
    "credits": "",
    "share_title": "",
    "about_sharing_label": "",
    "about_sharing_link": "",
    "email_subject": "",
    "email_body": "",
    "twitter_message": "",
    "onward_journeys_title": "",
    "onward_journey_url_1": "",
    "onward_journey_text_1": "",
    "onward_journey_img_url_1": "",
    "onward_journey_url_2": "",
    "onward_journey_text_2": "",
    "onward_journey_img_url_2": "",
    "onward_journey_url_3": "",
    "onward_journey_text_3": "",
    "onward_journey_img_url_3": "",
    "legacy_ie_message": ""
}